soundscape_generation/__init__.py
soundscape_generation/evaluation.py
soundscape_generation/predict.py
soundscape_generation/sound_generation.py
soundscape_generation/train.py
soundscape_generation/dataset/__init__.py
soundscape_generation/dataset/cityscapes.py
soundscape_generation/eval/__init__.py
soundscape_generation/eval/evaluation.py
soundscape_generation/generation/sound_generation.py
soundscape_generation/loss/__init__.py
soundscape_generation/loss/losses.py
soundscape_generation/models/ERFNet.py
soundscape_generation/models/__init__.py
soundscape_generation/utils/__init__.py
soundscape_generation/utils/utils.py
soundscape_generation-0.1.1.dist-info/METADATA
soundscape_generation-0.1.1.dist-info/WHEEL
soundscape_generation-0.1.1.dist-info/top_level.txt
soundscape_generation-0.1.1.dist-info/RECORD
