Metadata-Version: 2.1
Name: soundscape-generation
Version: 0.1.1
Summary: Generate soundscapes based on images.
Home-page: https://github.com/hslu-abiz/soundscape-generation
Author: ABIZ Lab
Author-email: abiz@hslu.ch
License: UNKNOWN
Keywords: soundscapes,generation,tensorflow
Platform: UNKNOWN
Classifier: Development Status :: 1 - Planning
Classifier: Intended Audience :: Science/Research
Classifier: License :: OSI Approved :: BSD License
Classifier: Operating System :: POSIX :: Linux
Classifier: Programming Language :: Python :: 2
Classifier: Programming Language :: Python :: 2.7
Classifier: Programming Language :: Python :: 3
Classifier: Programming Language :: Python :: 3.4
Classifier: Programming Language :: Python :: 3.5
